[
    {
        "name": "Standard Kart / The Duke / 300 SL Roadster",
        "speed": {
            "ground": 3,
            "water": 3,
            "air": 3,
            "antiGravity": 3
        },
        "acceleration": 4,
        "weight": 2,
        "handling": {
            "ground": 3,
            "water": 2,
            "air": 3,
            "antiGravity": 3
        },
        "traction": 3,
        "miniTurbo": 4,
        "sportBike": false
    },
    {
        "name": "Pipe Frame / Varmint / City Tripper",
        "speed": {
            "ground": 1,
            "water": 3,
            "air": 1,
            "antiGravity": 1
        },
        "acceleration": 6,
        "weight": 1,
        "handling": {
            "ground": 5,
            "water": 4,
            "air": 2,
            "antiGravity": 4
        },
        "traction": 4,
        "miniTurbo": 5,
        "sportBike": false
    },
    {
        "name": "Mach 8 / Spourts Coupe / Inkstriker",
        "speed": {
            "ground": 3,
            "water": 3,
            "air": 4,
            "antiGravity": 5
        },
        "acceleration": 3,
        "weight": 3,
        "handling": {
            "ground": 2,
            "water": 2,
            "air": 2,
            "antiGravity": 4
        },
        "traction": 4,
        "miniTurbo": 4,
        "sportBike": false
    },
    {
        "name": "Steel Driver / Tri-Speeder / Bone Rattler",
        "speed": {
            "ground": 4,
            "water": 5,
            "air": 0,
            "antiGravity": 2
        },
        "acceleration": 1,
        "weight": 4,
        "handling": {
            "ground": 1,
            "water": 5,
            "air": 1,
            "antiGravity": 1
        },
        "traction": 3,
        "miniTurbo": 2,
        "sportBike": false
    },
    {
        "name": "Cat Cruiser / Teddy Buggy",
        "speed": {
            "ground": 2,
            "water": 2,
            "air": 4,
            "antiGravity": 3
        },
        "acceleration": 5,
        "weight": 2,
        "handling": {
            "ground": 4,
            "water": 2,
            "air": 4,
            "antiGravity": 3
        },
        "traction": 3,
        "miniTurbo": 5,
        "sportBike": false
    },
    {
        "name": "Comet / Yoshi Bike",
        "speed": {
            "ground": 2,
            "water": 2,
            "air": 4,
            "antiGravity": 3
        },
        "acceleration": 5,
        "weight": 2,
        "handling": {
            "ground": 4,
            "water": 2,
            "air": 4,
            "antiGravity": 3
        },
        "traction": 3,
        "miniTurbo": 5,
        "sportBike": true
    },
    {
        "name": "Circuit Special / B Dasher / P-Wing",
        "speed": {
            "ground": 5,
            "water": 1,
            "air": 2,
            "antiGravity": 4
        },
        "acceleration": 1,
        "weight": 3,
        "handling": {
            "ground": 1,
            "water": 1,
            "air": 0,
            "antiGravity": 2
        },
        "traction": 1,
        "miniTurbo": 1,
        "sportBike": false
    },
    {
        "name": "Badwagon / Standard ATV / GLA",
        "speed": {
            "ground": 5,
            "water": 2,
            "air": 1,
            "antiGravity": 3
        },
        "acceleration": 0,
        "weight": 4,
        "handling": {
            "ground": 0,
            "water": 1,
            "air": 0,
            "antiGravity": 1
        },
        "traction": 5,
        "miniTurbo": 0,
        "sportBike": false
    },
    {
        "name": "Prancer",
        "speed": {
            "ground": 4,
            "water": 3,
            "air": 3,
            "antiGravity": 3
        },
        "acceleration": 2,
        "weight": 1,
        "handling": {
            "ground": 3,
            "water": 3,
            "air": 3,
            "antiGravity": 2
        },
        "traction": 2,
        "miniTurbo": 3,
        "sportBike": false
    },
    {
        "name": "Sport Bike / Jet Bike",
        "speed": {
            "ground": 4,
            "water": 3,
            "air": 3,
            "antiGravity": 3
        },
        "acceleration": 2,
        "weight": 1,
        "handling": {
            "ground": 3,
            "water": 3,
            "air": 3,
            "antiGravity": 2
        },
        "traction": 2,
        "miniTurbo": 3,
        "sportBike": true
    },
    {
        "name": "Biddybuggy / Mr. Scooty",
        "speed": {
            "ground": 0,
            "water": 1,
            "air": 1,
            "antiGravity": 2
        },
        "acceleration": 7,
        "weight": 0,
        "handling": {
            "ground": 5,
            "water": 4,
            "air": 4,
            "antiGravity": 5
        },
        "traction": 4,
        "miniTurbo": 7,
        "sportBike": false
    },
    {
        "name": "Landship / Streetle",
        "speed": {
            "ground": 1,
            "water": 5,
            "air": 2,
            "antiGravity": 0
        },
        "acceleration": 6,
        "weight": 0,
        "handling": {
            "ground": 4,
            "water": 5,
            "air": 3,
            "antiGravity": 2
        },
        "traction": 6,
        "miniTurbo": 6,
        "sportBike": false
    },
    {
        "name": "Sneeker / Gold Standard",
        "speed": {
            "ground": 4,
            "water": 2,
            "air": 3,
            "antiGravity": 3
        },
        "acceleration": 2,
        "weight": 2,
        "handling": {
            "ground": 3,
            "water": 2,
            "air": 2,
            "antiGravity": 3
        },
        "traction": 0,
        "miniTurbo": 3,
        "sportBike": false
    },
    
    {
        "name": "Master Cycle",
        "speed": {
            "ground": 4,
            "water": 2,
            "air": 3,
            "antiGravity": 3
        },
        "acceleration": 2,
        "weight": 2,
        "handling": {
            "ground": 3,
            "water": 2,
            "air": 2,
            "antiGravity": 3
        },
        "traction": 0,
        "miniTurbo": 3,
        "sportBike": true
    },
    {
        "name": "Standard Bike / Flame Rider / Wild Wiggler / W 25 Silver Arrow",
        "speed": {
            "ground": 2,
            "water": 2,
            "air": 3,
            "antiGravity": 4
        },
        "acceleration": 5,
        "weight": 1,
        "handling": {
            "ground": 4,
            "water": 3,
            "air": 3,
            "antiGravity": 4
        },
        "traction": 5,
        "miniTurbo": 5,
        "sportBike": false
    },
    {
        "name": "Blue Falcon / Splat Buggy",
        "speed": {
            "ground": 4,
            "water": 2,
            "air": 3,
            "antiGravity": 4
        },
        "acceleration": 3,
        "weight": 0,
        "handling": {
            "ground": 2,
            "water": 3,
            "air": 1,
            "antiGravity": 5
        },
        "traction": 3,
        "miniTurbo": 3,
        "sportBike": false
    },
    {
        "name": "Tanooki Kart / Koopa Clown / Master Cycle Zero",
        "speed": {
            "ground": 2,
            "water": 4,
            "air": 3,
            "antiGravity": 3
        },
        "acceleration": 2,
        "weight": 3,
        "handling": {
            "ground": 4,
            "water": 4,
            "air": 3,
            "antiGravity": 3
        },
        "traction": 7,
        "miniTurbo": 3,
        "sportBike": false
    }
]